{
  "owner": "PCE",
  "table": "PCEADMISSOES",
  "colunas": [
    {
      "nome": "INT_EPISODIO",
      "tipo": "NUMBER",
      "tamanho": 22,
      "precisao": 8,
      "escala": 0,
      "nullable": false,
      "default": null,
      "posicao": 1
    },
    {
      "nome": "NUM_MECANOGRAFICO",
      "tipo": "NUMBER",
      "tamanho": 22,
      "precisao": 5,
      "escala": 0,
      "nullable": true,
      "default": null,
      "posicao": 2
    },
    {
      "nome": "NUM_SEQUENCIAL",
      "tipo": "NUMBER",
      "tamanho": 22,
      "precisao": 8,
      "escala": 0,
      "nullable": true,
      "default": null,
      "posicao": 3
    },
    {
      "nome": "DTA_INTERNAMENTO",
      "tipo": "DATE",
      "tamanho": 7,
      "precisao": null,
      "escala": null,
      "nullable": true,
      "default": null,
      "posicao": 4
    },
    {
      "nome": "HORA_INTERNAMENTO",
      "tipo": "NUMBER",
      "tamanho": 22,
      "precisao": 5,
      "escala": 0,
      "nullable": true,
      "default": null,
      "posicao": 5
    },
    {
      "nome": "TIPO_ADMISSAO",
      "tipo": "CHAR",
      "tamanho": 1,
      "precisao": null,
      "escala": null,
      "nullable": true,
      "default": null,
      "posicao": 6
    },
    {
      "nome": "COD_PROVENIENCIA",
      "tipo": "NUMBER",
      "tamanho": 22,
      "precisao": 2,
      "escala": 0,
      "nullable": true,
      "default": null,
      "posicao": 7
    },
    {
      "nome": "COD_UNID_SAUDE_PROV",
      "tipo": "NUMBER",
      "tamanho": 22,
      "precisao": 7,
      "escala": 0,
      "nullable": true,
      "default": null,
      "posicao": 8
    },
    {
      "nome": "COD_ESPECIALIDADE_PROV",
      "tipo": "NUMBER",
      "tamanho": 22,
      "precisao": 5,
      "escala": 0,
      "nullable": true,
      "default": null,
      "posicao": 9
    },
    {
      "nome": "NUM_EPISODIO_PROV",
      "tipo": "NUMBER",
      "tamanho": 22,
      "precisao": 8,
      "escala": 0,
      "nullable": true,
      "default": null,
      "posicao": 10
    },
    {
      "nome": "COD_SUBSISTEMA_RESP",
      "tipo": "NUMBER",
      "tamanho": 22,
      "precisao": 6,
      "escala": 0,
      "nullable": true,
      "default": null,
      "posicao": 11
    },
    {
      "nome": "NUM_BENEFICIARIO",
      "tipo": "VARCHAR2",
      "tamanho": 20,
      "precisao": null,
      "escala": null,
      "nullable": true,
      "default": null,
      "posicao": 12
    },
    {
      "nome": "DTA_ANULA",
      "tipo": "DATE",
      "tamanho": 7,
      "precisao": null,
      "escala": null,
      "nullable": true,
      "default": null,
      "posicao": 13
    },
    {
      "nome": "REMOVER",
      "tipo": "NUMBER",
      "tamanho": 22,
      "precisao": 1,
      "escala": 0,
      "nullable": true,
      "default": null,
      "posicao": 14
    }
  ],
  "constraints": {
    "SYS_C0010000": {
      "tipo": "P",
      "colunas": [
        "INT_EPISODIO"
      ],
      "condicao": null,
      "tabelaRef": null
    }
  },
  "indices": {
    "IPCEADM": {
      "unico": false,
      "colunas": [
        "NUM_SEQUENCIAL"
      ]
    },
    "PCEADMISSOESIDX01": {
      "unico": false,
      "colunas": [
        "INT_EPISODIO",
        "NUM_SEQUENCIAL"
      ]
    },
    "SYS_C0010000": {
      "unico": true,
      "colunas": [
        "INT_EPISODIO"
      ]
    }
  },
  "totalRegistros": 28768
}