{
  "owner": "PCE",
  "table": "PRF_INTER_JUSTIFICA",
  "colunas": [
    {
      "nome": "ID_PRESC",
      "tipo": "NUMBER",
      "tamanho": 22,
      "precisao": 10,
      "escala": 0,
      "nullable": true,
      "default": null,
      "posicao": 1
    },
    {
      "nome": "JUSTIFICA",
      "tipo": "VARCHAR2",
      "tamanho": 100,
      "precisao": null,
      "escala": null,
      "nullable": true,
      "default": null,
      "posicao": 2
    },
    {
      "nome": "OBSERVA",
      "tipo": "VARCHAR2",
      "tamanho": 4000,
      "precisao": null,
      "escala": null,
      "nullable": true,
      "default": null,
      "posicao": 3
    },
    {
      "nome": "DATA_REG",
      "tipo": "DATE",
      "tamanho": 7,
      "precisao": null,
      "escala": null,
      "nullable": true,
      "default": null,
      "posicao": 4
    },
    {
      "nome": "USER_REG",
      "tipo": "VARCHAR2",
      "tamanho": 20,
      "precisao": null,
      "escala": null,
      "nullable": true,
      "default": null,
      "posicao": 5
    }
  ],
  "constraints": null,
  "indices": null,
  "totalRegistros": 2
}